Workbook

Sheet Dashboard
B1: CONTROLE FINANCEIRO PESSOAL
B3: Dashboard automático para acompanhar entradas, saídas, investimentos e contas a pagar
B5: Saldo Atual | E5: Entradas | H5: Saídas | K5: Investimentos
B6: =SUM(Entradas!E:E)-SUM(Saidas!F:F) | E6: =SUM(Entradas!E:E) | H6: =SUM(Saidas!F:F) | K6: =SUM(Investimentos!E:E)
B9: Como usar: registre seus valores nas abas Entradas, Saidas, Investimentos e Contas_a_Pagar. O Dashboard atualiza os totais e gráficos automaticamente. | G9: Cores: azul = campos de preenchimento, preto = fórmulas, vermelho = alerta/atraso, roxo = controle/investimentos. | K9: Dica: use as listas suspensas de categoria/status para manter os gráficos corretos.
B15: Resumo Mensal | G15: Despesas por Categoria | K15: Contas a Pagar
B16: Mês | C16: Entradas | D16: Saídas | E16: Saldo | G16: Categoria | H16: Total | K16: Indicador | L16: Valor
B17: Jan | C17: =SUMIFS(Entradas!$E:$E,Entradas!$A:$A,">="&DATE(YEAR(TODAY()),1,1),Entradas!$A:$A,"<"&EDATE(DATE(YEAR(TODAY()),1,1),1)) | D17: =SUMIFS(Saidas!$F:$F,Saidas!$A:$A,">="&DATE(YEAR(TODAY()),1,1),Saidas!$A:$A,"<"&EDATE(DATE(YEAR(TODAY()),1,1),1)) | E17: =C17-D17 | G17: Moradia | H17: =SUMIF(Saidas!$D:$D,G17,Saidas!$F:$F) | K17: Total em aberto | L17: =SUMIFS(Contas_a_Pagar!D:D,Contas_a_Pagar!E:E,"Não")
B18: Fev | C18: =SUMIFS(Entradas!$E:$E,Entradas!$A:$A,">="&DATE(YEAR(TODAY()),2,1),Entradas!$A:$A,"<"&EDATE(DATE(YEAR(TODAY()),2,1),1)) | D18: =SUMIFS(Saidas!$F:$F,Saidas!$A:$A,">="&DATE(YEAR(TODAY()),2,1),Saidas!$A:$A,"<"&EDATE(DATE(YEAR(TODAY()),2,1),1)) | E18: =C18-D18 | G18: Alimentação | H18: =SUMIF(Saidas!$D:$D,G18,Saidas!$F:$F) | K18: Total pago | L18: =SUMIFS(Contas_a_Pagar!D:D,Contas_a_Pagar!E:E,"Sim")
B19: Mar | C19: =SUMIFS(Entradas!$E:$E,Entradas!$A:$A,">="&DATE(YEAR(TODAY()),3,1),Entradas!$A:$A,"<"&EDATE(DATE(YEAR(TODAY()),3,1),1)) | D19: =SUMIFS(Saidas!$F:$F,Saidas!$A:$A,">="&DATE(YEAR(TODAY()),3,1),Saidas!$A:$A,"<"&EDATE(DATE(YEAR(TODAY()),3,1),1)) | E19: =C19-D19 | G19: Transporte | H19: =SUMIF(Saidas!$D:$D,G19,Saidas!$F:$F) | K19: Atrasadas | L19: =SUMIFS(Contas_a_Pagar!D:D,Contas_a_Pagar!G:G,"Sim")
B20: Abr | C20: =SUMIFS(Entradas!$E:$E,Entradas!$A:$A,">="&DATE(YEAR(TODAY()),4,1),Entradas!$A:$A,"<"&EDATE(DATE(YEAR(TODAY()),4,1),1)) | D20: =SUMIFS(Saidas!$F:$F,Saidas!$A:$A,">="&DATE(YEAR(TODAY()),4,1),Saidas!$A:$A,"<"&EDATE(DATE(YEAR(TODAY()),4,1),1)) | E20: =C20-D20 | G20: Saúde | H20: =SUMIF(Saidas!$D:$D,G20,Saidas!$F:$F)
B21: Mai | C21: =SUMIFS(Entradas!$E:$E,Entradas!$A:$A,">="&DATE(YEAR(TODAY()),5,1),Entradas!$A:$A,"<"&EDATE(DATE(YEAR(TODAY()),5,1),1)) | D21: =SUMIFS(Saidas!$F:$F,Saidas!$A:$A,">="&DATE(YEAR(TODAY()),5,1),Saidas!$A:$A,"<"&EDATE(DATE(YEAR(TODAY()),5,1),1)) | E21: =C21-D21 | G21: Educação | H21: =SUMIF(Saidas!$D:$D,G21,Saidas!$F:$F)
B22: Jun | C22: =SUMIFS(Entradas!$E:$E,Entradas!$A:$A,">="&DATE(YEAR(TODAY()),6,1),Entradas!$A:$A,"<"&EDATE(DATE(YEAR(TODAY()),6,1),1)) | D22: =SUMIFS(Saidas!$F:$F,Saidas!$A:$A,">="&DATE(YEAR(TODAY()),6,1),Saidas!$A:$A,"<"&EDATE(DATE(YEAR(TODAY()),6,1),1)) | E22: =C22-D22 | G22: Lazer | H22: =SUMIF(Saidas!$D:$D,G22,Saidas!$F:$F)
B23: Jul | C23: =SUMIFS(Entradas!$E:$E,Entradas!$A:$A,">="&DATE(YEAR(TODAY()),7,1),Entradas!$A:$A,"<"&EDATE(DATE(YEAR(TODAY()),7,1),1)) | D23: =SUMIFS(Saidas!$F:$F,Saidas!$A:$A,">="&DATE(YEAR(TODAY()),7,1),Saidas!$A:$A,"<"&EDATE(DATE(YEAR(TODAY()),7,1),1)) | E23: =C23-D23 | G23: Assinaturas | H23: =SUMIF(Saidas!$D:$D,G23,Saidas!$F:$F)
B24: Ago | C24: =SUMIFS(Entradas!$E:$E,Entradas!$A:$A,">="&DATE(YEAR(TODAY()),8,1),Entradas!$A:$A,"<"&EDATE(DATE(YEAR(TODAY()),8,1),1)) | D24: =SUMIFS(Saidas!$F:$F,Saidas!$A:$A,">="&DATE(YEAR(TODAY()),8,1),Saidas!$A:$A,"<"&EDATE(DATE(YEAR(TODAY()),8,1),1)) | E24: =C24-D24 | G24: Outros | H24: =SUMIF(Saidas!$D:$D,G24,Saidas!$F:$F)
B25: Set | C25: =SUMIFS(Entradas!$E:$E,Entradas!$A:$A,">="&DATE(YEAR(TODAY()),9,1),Entradas!$A:$A,"<"&EDATE(DATE(YEAR(TODAY()),9,1),1)) | D25: =SUMIFS(Saidas!$F:$F,Saidas!$A:$A,">="&DATE(YEAR(TODAY()),9,1),Saidas!$A:$A,"<"&EDATE(DATE(YEAR(TODAY()),9,1),1)) | E25: =C25-D25
B26: Out | C26: =SUMIFS(Entradas!$E:$E,Entradas!$A:$A,">="&DATE(YEAR(TODAY()),10,1),Entradas!$A:$A,"<"&EDATE(DATE(YEAR(TODAY()),10,1),1)) | D26: =SUMIFS(Saidas!$F:$F,Saidas!$A:$A,">="&DATE(YEAR(TODAY()),10,1),Saidas!$A:$A,"<"&EDATE(DATE(YEAR(TODAY()),10,1),1)) | E26: =C26-D26
B27: Nov | C27: =SUMIFS(Entradas!$E:$E,Entradas!$A:$A,">="&DATE(YEAR(TODAY()),11,1),Entradas!$A:$A,"<"&EDATE(DATE(YEAR(TODAY()),11,1),1)) | D27: =SUMIFS(Saidas!$F:$F,Saidas!$A:$A,">="&DATE(YEAR(TODAY()),11,1),Saidas!$A:$A,"<"&EDATE(DATE(YEAR(TODAY()),11,1),1)) | E27: =C27-D27
B28: Dez | C28: =SUMIFS(Entradas!$E:$E,Entradas!$A:$A,">="&DATE(YEAR(TODAY()),12,1),Entradas!$A:$A,"<"&EDATE(DATE(YEAR(TODAY()),12,1),1)) | D28: =SUMIFS(Saidas!$F:$F,Saidas!$A:$A,">="&DATE(YEAR(TODAY()),12,1),Saidas!$A:$A,"<"&EDATE(DATE(YEAR(TODAY()),12,1),1)) | E28: =C28-D28

Sheet Entradas
A1: Entradas de Valores
A4: Data | B4: Descrição | C4: Fonte | D4: Tipo | E4: Categoria | F4: Valor | G4: Observações | I4: Dicas
I5: Fonte = origem do dinheiro
I6: Tipo = fixa, variável, recorrente ou extra
I7: Categoria = classificação da entrada
I8: Use as setas das células para selecionar

Sheet Saidas
A1: Saídas / Despesas
A4: Data | B4: Descrição | C4: Tipo | D4: Categoria | E4: Forma Pagamento | F4: Valor | G4: Observações | I4: Orientação
I5: Preencha as linhas em azul. Os totais e gráficos serão calculados automaticamente no Dashboard.

Sheet Investimentos
A1: Controle de Investimentos
A4: Data | B4: Ativo | C4: Tipo | D4: Corretora/Banco | E4: Valor Aplicado | F4: Rentabilidade (%) | G4: Valor Atual | I4: Orientação
G5: =IF(E5="","",E5*(1+F5/100)) | I5: Preencha as linhas em azul. Os totais e gráficos serão calculados automaticamente no Dashboard.
G6: =IF(E6="","",E6*(1+F6/100))
G7: =IF(E7="","",E7*(1+F7/100))
G8: =IF(E8="","",E8*(1+F8/100))
G9: =IF(E9="","",E9*(1+F9/100))
G10: =IF(E10="","",E10*(1+F10/100))
G11: =IF(E11="","",E11*(1+F11/100))
G12: =IF(E12="","",E12*(1+F12/100))
G13: =IF(E13="","",E13*(1+F13/100))
G14: =IF(E14="","",E14*(1+F14/100))
G15: =IF(E15="","",E15*(1+F15/100))
G16: =IF(E16="","",E16*(1+F16/100))
G17: =IF(E17="","",E17*(1+F17/100))
... G504: =IF(E504="","",E504*(1+F504/100))

Sheet Contas_a_Pagar
A1: Contas a Pagar
A4: Vencimento | B4: Descrição | C4: Categoria | D4: Valor | E4: Pago? | F4: Data Pagamento | G4: Atrasada? | H4: Observações | J4: Orientação
G5: =IF(AND(A5<TODAY(),E5<>"Sim"),"Sim","Não") | J5: Preencha as linhas em azul. Os totais e gráficos serão calculados automaticamente no Dashboard.
G6: =IF(AND(A6<TODAY(),E6<>"Sim"),"Sim","Não")
G7: =IF(AND(A7<TODAY(),E7<>"Sim"),"Sim","Não")
G8: =IF(AND(A8<TODAY(),E8<>"Sim"),"Sim","Não")
G9: =IF(AND(A9<TODAY(),E9<>"Sim"),"Sim","Não")
G10: =IF(AND(A10<TODAY(),E10<>"Sim"),"Sim","Não")
G11: =IF(AND(A11<TODAY(),E11<>"Sim"),"Sim","Não")
G12: =IF(AND(A12<TODAY(),E12<>"Sim"),"Sim","Não")
G13: =IF(AND(A13<TODAY(),E13<>"Sim"),"Sim","Não")
G14: =IF(AND(A14<TODAY(),E14<>"Sim"),"Sim","Não")
G15: =IF(AND(A15<TODAY(),E15<>"Sim"),"Sim","Não")
G16: =IF(AND(A16<TODAY(),E16<>"Sim"),"Sim","Não")
G17: =IF(AND(A17<TODAY(),E17<>"Sim"),"Sim","Não")
... G504: =IF(AND(A504<TODAY(),E504<>"Sim"),"Sim","Não")

Sheet Resumo_Anual
A1: Resumo Anual e Metas
A4: Indicador | B4: Valor | H4: Orientação
A5: Total Entradas | B5: =SUM(Entradas!E:E) | H5: Preencha as linhas em azul. Os totais e gráficos serão calculados automaticamente no Dashboard.
A6: Total Saídas | B6: =SUM(Saidas!F:F)
A7: Saldo Final | B7: =B5-B6
A8: Total Investido | B8: =SUM(Investimentos!E:E)
A9: Patrimônio Atual Investimentos | B9: =SUM(Investimentos!G:G)
A10: Contas em Aberto | B10: =SUMIFS(Contas_a_Pagar!D:D,Contas_a_Pagar!E:E,"Não")

Sheet Listas
A1: Fontes_Entrada | B1: Categorias_Entrada | C1: Tipos_Entrada
A2: Salário | B2: Salário | C2: Fixa
A3: Freelance | B3: Freelance | C3: Variável
A4: Renda Extra | B4: Renda Extra | C4: Recorrente
A5: Comissão | B5: Investimentos | C5: Extra
A6: 13º Salário | B6: Reembolso
A7: PLR | B7: Venda
A8: Venda | B8: Bonificação
A9: Reembolso | B9: Presente
A10: Presente | B10: Cashback
A11: Cashback | B11: Outros
A12: Rendimentos
A13: Outros
